LICENSE
README.md
setup.cfg
setup.py
consnet/__init__.py
consnet.egg-info/PKG-INFO
consnet.egg-info/SOURCES.txt
consnet.egg-info/dependency_links.txt
consnet.egg-info/requires.txt
consnet.egg-info/top_level.txt
consnet/api/__init__.py
consnet/api/bbox.py
consnet/api/data.py
consnet/api/evaluation.py
consnet/api/static.py
consnet/datasets/__init__.py
consnet/datasets/builder.py
consnet/datasets/hico_det.py
consnet/models/__init__.py
consnet/models/builder.py
consnet/models/consnet.py
consnet/models/blocks/__init__.py
consnet/models/blocks/confidence.py
consnet/models/blocks/fusion.py
consnet/models/blocks/mapper.py
consnet/models/blocks/semantic.py
consnet/models/detectors/__init__.py
consnet/models/detectors/hooked_bbox_head.py
consnet/models/detectors/hooked_rcnn.py
consnet/models/detectors/hooked_roi_head.py
consnet/models/embedders/__init__.py
consnet/models/embedders/elmo.py
consnet/models/losses/__init__.py
consnet/models/losses/dynamic_bce_loss.py