Metadata-Version: 2.1
Name: consnet
Version: 1.2.0
Summary: A general toolkit for human-object interaction detection
Home-page: https://github.com/yeliudev/ConsNet
Author: Ye Liu
Author-email: yeliudev@outlook.com
License: GPLv3
Platform: UNKNOWN
Classifier: Development Status :: 5 - Production/Stable
Classifier: License :: OSI Approved :: GNU General Public License v3 (GPLv3)
Classifier: Operating System :: OS Independent
Classifier: Programming Language :: Python :: 3
Classifier: Programming Language :: Python :: 3.8
Classifier: Programming Language :: Python :: 3.9
Classifier: Programming Language :: Python :: 3.10
Classifier: Topic :: Utilities
Requires-Python: >=3.8
Provides-Extra: full
License-File: LICENSE
